nasdaq_stock_quote/__init__.py
nasdaq_stock_quote-0.1.1.dist-info/DESCRIPTION.rst
nasdaq_stock_quote-0.1.1.dist-info/METADATA
nasdaq_stock_quote-0.1.1.dist-info/RECORD
nasdaq_stock_quote-0.1.1.dist-info/WHEEL
nasdaq_stock_quote-0.1.1.dist-info/metadata.json
nasdaq_stock_quote-0.1.1.dist-info/top_level.txt
