Metadata-Version: 2.0
Name: nasdaq-stock-quote
Version: 0.1.1
Summary: NASDAQ Common Stock Quote & Summary Data Scraper
Home-page: https://github.com/AndrewRPorter/nasdaq-stock-quote
Author: Andrew Porter
Author-email: porter.r.andrew@gmail.com
License: MIT License
Requires-Dist: lxml
Requires-Dist: requests
Requires-Dist: setuptools
